{
    "openapi": "3.0.0",
    "info": {
        "title": "Yeungjin-Global",
        "description": "YJG API Documentation",
        "version": "0.1"
    },
    "paths": {
        "/api/admin": {
            "get": {
                "tags": [
                    "관리자"
                ],
                "summary": "승인 혹은 미승인 관리자 목록",
                "description": "파라미터 값에 맞는 관리자를 admins 배열에 반환",
                "operationId": "1aa48cc3a601191997d32b65056c2b17",
                "requestBody": {
                    "description": "승인 관리자 조회의 경우 approved, 미승인 관리자 조회의 경우 unapproved, 전체 조회 시에는 body 없이 요청만",
                    "required": false,
                    "content": {
                        "application/json": {
                            "schema": {
                                "properties": {
                                    "type": {
                                        "description": "승인 미승인 여부",
                                        "type": "string",
                                        "example": "approved"
                                    }
                                },
                                "type": "object"
                            }
                        }
                    }
                },
                "responses": {
                    "200": {
                        "description": "Success"
                    },
                    "500": {
                        "description": "Server Error"
                    }
                }
            },
            "post": {
                "tags": [
                    "관리자"
                ],
                "summary": "회원가입",
                "description": "관리자 회원가입",
                "operationId": "93a50f4facd7dd356c2551cec4d799ca",
                "requestBody": {
                    "description": "관리자 회원가입 정보",
                    "required": true,
                    "content": {
                        "application/json": {
                            "schema": {
                                "properties": {
                                    "name": {
                                        "description": "사용자 이름",
                                        "type": "string",
                                        "example": "관리자"
                                    },
                                    "phone_number": {
                                        "description": "전화번호",
                                        "type": "string",
                                        "example": "01012345678"
                                    },
                                    "email": {
                                        "description": "이메일",
                                        "type": "string",
                                        "example": "admin@gmail.com"
                                    },
                                    "password": {
                                        "description": "비밀번호",
                                        "type": "string",
                                        "example": "admin123"
                                    }
                                },
                                "type": "object"
                            }
                        }
                    }
                },
                "responses": {
                    "200": {
                        "description": "Success"
                    },
                    "500": {
                        "description": "Fail"
                    }
                }
            },
            "patch": {
                "tags": [
                    "관리자"
                ],
                "summary": "개인정보 수정",
                "description": "관리자 개인정보 수정",
                "operationId": "f0fe63e23f0955f57c772d77e62889e4",
                "requestBody": {
                    "description": "수정할 관리자 정보",
                    "required": true,
                    "content": {
                        "application/json": {
                            "schema": {
                                "properties": {
                                    "admin_id": {
                                        "description": "정보를 수정할 관리자의 아이디",
                                        "type": "number",
                                        "example": 1
                                    },
                                    "name": {
                                        "description": "변경할 이름",
                                        "type": "string",
                                        "example": "hyun"
                                    },
                                    "phone_number": {
                                        "description": "변경할 휴대폰 번호",
                                        "type": "string",
                                        "example": "01012345678"
                                    },
                                    "password": {
                                        "description": "변경할 비밀번호",
                                        "type": "string",
                                        "example": "asdf123"
                                    }
                                },
                                "type": "object"
                            }
                        }
                    }
                },
                "responses": {
                    "200": {
                        "description": "Success"
                    },
                    "500": {
                        "description": "Fail"
                    }
                }
            }
        },
        "/api/admin/{id}": {
            "delete": {
                "tags": [
                    "관리자"
                ],
                "summary": "탈퇴",
                "description": "관리자 탈퇴",
                "operationId": "dd4995c3a6252650b5a00f9bf0fe0327",
                "parameters": [
                    {
                        "name": "id",
                        "in": "path",
                        "description": "탈퇴할 관리자의 아이디",
                        "required": true,
                        "schema": {
                            "type": "integer"
                        }
                    }
                ],
                "responses": {
                    "200": {
                        "description": "Success"
                    },
                    "500": {
                        "description": "Fail"
                    }
                }
            }
        },
        "/api/admin/login": {
            "post": {
                "tags": [
                    "관리자"
                ],
                "summary": "로그인",
                "description": "관리자 로그인. 요청 시 /sanctum/csrf-coocie 경로로 먼저 요청 보내고 로그인 시도하기",
                "operationId": "ee8b4f31d1a5652cb5942d928603e931",
                "requestBody": {
                    "description": "관리자 로그인을 위한 정보",
                    "required": true,
                    "content": {
                        "application/json": {
                            "schema": {
                                "properties": {
                                    "email": {
                                        "description": "이메일",
                                        "type": "string",
                                        "example": "admin@gmail.com"
                                    },
                                    "password": {
                                        "description": "비밀번호",
                                        "type": "string",
                                        "example": "admin123"
                                    }
                                },
                                "type": "object"
                            }
                        }
                    }
                },
                "responses": {
                    "200": {
                        "description": "Success"
                    },
                    "500": {
                        "description": "Fail"
                    }
                }
            }
        },
        "/api/admin/logout": {
            "post": {
                "tags": [
                    "관리자"
                ],
                "summary": "로그아웃",
                "description": "관리자 로그아웃",
                "operationId": "6aab0886c63cb87c77d644c8e51c3b83",
                "responses": {
                    "200": {
                        "description": "Success"
                    },
                    "500": {
                        "description": "Fail"
                    }
                }
            }
        },
        "/api/admin/privilege": {
            "patch": {
                "tags": [
                    "관리자"
                ],
                "summary": "권한 변경",
                "description": "관리자 권한 변경",
                "operationId": "34229bc1cfc14b18a8f1838ce8db3d18",
                "requestBody": {
                    "description": "관리자 권한 변경을 위한 값 및 아이디",
                    "required": true,
                    "content": {
                        "application/json": {
                            "schema": {
                                "properties": {
                                    "id": {
                                        "description": "권한을 부여할 유저 아이디",
                                        "type": "number",
                                        "example": 1
                                    },
                                    "salon_privilege": {
                                        "description": "미용실 권한",
                                        "type": "boolean",
                                        "example": true
                                    },
                                    "admin_privilege": {
                                        "description": "행정 권한",
                                        "type": "boolean",
                                        "example": true
                                    },
                                    "restaurant_privilege": {
                                        "description": "식당 권한",
                                        "type": "boolean",
                                        "example": true
                                    }
                                },
                                "type": "object"
                            }
                        }
                    }
                },
                "responses": {
                    "200": {
                        "description": "Success"
                    },
                    "500": {
                        "description": "Fail"
                    }
                }
            }
        },
        "/api/admin/approve": {
            "patch": {
                "tags": [
                    "관리자"
                ],
                "summary": "회원가입 승인",
                "description": "관리자 회원가입 승인 (거부 시 계정 정보 삭제 됨)",
                "operationId": "53e00267ec8c72df658417c9c01ae034",
                "requestBody": {
                    "description": "아이디 및 승인 여부",
                    "required": true,
                    "content": {
                        "application/json": {
                            "schema": {
                                "properties": {
                                    "admin_id": {
                                        "description": "권한을 부여할 관리자의 아이디",
                                        "type": "number",
                                        "example": 1
                                    },
                                    "approve": {
                                        "description": "관리자 회원가입 승인 여부",
                                        "type": "boolean",
                                        "example": false
                                    }
                                },
                                "type": "object"
                            }
                        }
                    }
                },
                "responses": {
                    "200": {
                        "description": "Success"
                    },
                    "500": {
                        "description": "Fail"
                    }
                }
            }
        },
        "/api/admin/verify-email/{id}": {
            "get": {
                "tags": [
                    "관리자"
                ],
                "summary": "이메일 중복 확인",
                "description": "관리자 이메일 중복 확인",
                "operationId": "ed9a1699e49fa1427b90ffb5a6dd6637",
                "parameters": [
                    {
                        "name": "id",
                        "in": "path",
                        "description": "중복을 확인할 관리자의 이메일",
                        "required": true,
                        "schema": {
                            "type": "string"
                        }
                    }
                ],
                "responses": {
                    "200": {
                        "description": "Success"
                    },
                    "422": {
                        "description": "Validation Error"
                    }
                }
            }
        },
        "/api/admin/verify-password": {
            "post": {
                "tags": [
                    "관리자"
                ],
                "summary": "PW 체크",
                "description": "관리자 회원정보 수정 페이지 접속 시 PW 체크",
                "operationId": "12bd4782914028b06286dda93a3a0d41",
                "requestBody": {
                    "description": "PW",
                    "required": true,
                    "content": {
                        "application/json": {
                            "schema": {
                                "properties": {
                                    "password": {
                                        "description": "비밀번호",
                                        "type": "string",
                                        "example": "admin123"
                                    }
                                },
                                "type": "object"
                            }
                        }
                    }
                },
                "responses": {
                    "200": {
                        "description": "Success"
                    },
                    "500": {
                        "description": "Fail"
                    }
                }
            }
        },
        "/api/admin/find-email": {
            "post": {
                "tags": [
                    "관리자"
                ],
                "summary": "이메일 찾기",
                "description": "회원가입 시 입력한 이름과 전화번호를 통하여 일치하는 값을 가진 이메일을 찾음",
                "operationId": "b443fe54d453512bf0dcfe4311ea2912",
                "requestBody": {
                    "description": "name & phone_number(without hyphen)",
                    "required": true,
                    "content": {
                        "application/json": {
                            "schema": {
                                "properties": {
                                    "name": {
                                        "description": "이름",
                                        "type": "string",
                                        "example": "testname"
                                    },
                                    "phone_number": {
                                        "description": "휴대폰 번호",
                                        "type": "string",
                                        "example": "01012345678"
                                    }
                                },
                                "type": "object"
                            }
                        }
                    }
                },
                "responses": {
                    "200": {
                        "description": "Success"
                    },
                    "404": {
                        "description": "Model Not Found(해당 하는 값이 없음)"
                    },
                    "422": {
                        "description": "Unprocessable Content(Request body에 올바르게 값을 입력했는지 확인)"
                    }
                }
            }
        },
        "/api/admin/salon-reservation": {
            "get": {
                "tags": [
                    "미용실"
                ],
                "summary": "예약 검색",
                "description": "미용실 예약 검색",
                "operationId": "259e551390c073313c7e33be1e6f7d86",
                "requestBody": {
                    "description": "검색할 옵션",
                    "required": true,
                    "content": {
                        "application/json": {
                            "schema": {
                                "properties": {
                                    "status": {
                                        "description": "예약의 상태(submit confirm reject 중 하나로 보내면 됨)",
                                        "type": "char",
                                        "example": "submit"
                                    },
                                    "r_date": {
                                        "description": "검색일",
                                        "type": "string",
                                        "format": "date",
                                        "example": "2001-01-29"
                                    },
                                    "r_time": {
                                        "description": "검색 시간",
                                        "type": "time",
                                        "example": "12:00:00"
                                    }
                                },
                                "type": "object"
                            }
                        }
                    }
                },
                "responses": {
                    "200": {
                        "description": "OK"
                    },
                    "422": {
                        "description": "Validation Exception"
                    },
                    "500": {
                        "description": "Fail"
                    }
                }
            },
            "patch": {
                "tags": [
                    "미용실"
                ],
                "summary": "예약 정보 업데이트(관리자)",
                "description": "미용실 예약 상태를 업데이트",
                "operationId": "b37a047096d300cdb4f8f84849feb261",
                "requestBody": {
                    "description": "업데이트할 상태 및 아이디",
                    "required": true,
                    "content": {
                        "application/json": {
                            "schema": {
                                "properties": {
                                    "id": {
                                        "description": "예약 아이디",
                                        "type": "integer",
                                        "example": 1
                                    },
                                    "status": {
                                        "description": "true로 보내면 승인, false로 보내면 거절",
                                        "type": "boolean",
                                        "example": true
                                    }
                                },
                                "type": "object"
                            }
                        }
                    }
                },
                "responses": {
                    "200": {
                        "description": "OK"
                    },
                    "422": {
                        "description": "Validation Exception"
                    },
                    "500": {
                        "description": "Fail"
                    }
                }
            }
        },
        "/api/admin/salon-break": {
            "post": {
                "tags": [
                    "미용실"
                ],
                "summary": "예약불가 시간 생성",
                "description": "미용실 예약불가 시간 생성",
                "operationId": "52ecb833b9a6df070383d99b22a39d2e",
                "requestBody": {
                    "description": "예약불가 시간 관련 정보",
                    "required": true,
                    "content": {
                        "application/json": {
                            "schema": {
                                "properties": {
                                    "s_time": {
                                        "description": "예약불가 시작",
                                        "type": "time",
                                        "example": "08:00:00"
                                    },
                                    "e_time": {
                                        "description": "예약불가 종료",
                                        "type": "time",
                                        "example": "21:00:00"
                                    },
                                    "date": {
                                        "description": "날짜",
                                        "type": "string",
                                        "format": "date",
                                        "example": "2024-01-01"
                                    }
                                },
                                "type": "object"
                            }
                        }
                    }
                },
                "responses": {
                    "201": {
                        "description": "Created"
                    },
                    "422": {
                        "description": "Validation Exception"
                    },
                    "500": {
                        "description": "Fail"
                    }
                }
            },
            "delete": {
                "tags": [
                    "미용실"
                ],
                "summary": "예약불가 시간 삭제",
                "description": "미용실 예약불가 시간 삭제",
                "operationId": "48e5d6302d31c25e801f2e8689ec7a08",
                "requestBody": {
                    "description": "예약불가 시간 관련 정보",
                    "required": true,
                    "content": {
                        "application/json": {
                            "schema": {
                                "properties": {
                                    "break_time": {
                                        "description": "삭제할 예약불가 시간",
                                        "type": "time",
                                        "example": "08:00:00"
                                    },
                                    "date": {
                                        "description": "삭제할 날짜",
                                        "type": "string",
                                        "format": "date",
                                        "example": "2024-01-01"
                                    }
                                },
                                "type": "object"
                            }
                        }
                    }
                },
                "responses": {
                    "200": {
                        "description": "Success"
                    },
                    "422": {
                        "description": "Validation Exception"
                    },
                    "500": {
                        "description": "Fail"
                    }
                }
            }
        },
        "/api/admin/salon-hour": {
            "post": {
                "tags": [
                    "미용실"
                ],
                "summary": "영업시간 생성",
                "description": "미용실 영업시간 생성",
                "operationId": "c8eca7e18f01818dc7b2c55b429f3f1c",
                "requestBody": {
                    "description": "영업시간 관련 정보",
                    "required": true,
                    "content": {
                        "application/json": {
                            "schema": {
                                "properties": {
                                    "s_time": {
                                        "description": "영업 시작",
                                        "type": "time",
                                        "example": "08:00:00"
                                    },
                                    "e_time": {
                                        "description": "영업 종료",
                                        "type": "time",
                                        "example": "21:00:00"
                                    },
                                    "date": {
                                        "description": "요일(대문자, 기존 DB 내에 중복 값 없어야함)",
                                        "type": "string",
                                        "format": "date",
                                        "example": "MON"
                                    }
                                },
                                "type": "object"
                            }
                        }
                    }
                },
                "responses": {
                    "201": {
                        "description": "Created"
                    },
                    "422": {
                        "description": "Validation Exception"
                    },
                    "500": {
                        "description": "Fail"
                    }
                }
            },
            "patch": {
                "tags": [
                    "미용실"
                ],
                "summary": "영업시간 업데이트",
                "description": "미용실 영업시간을 업데이트",
                "operationId": "0b5f8fdf523f60db21c8583b62c2bc0b",
                "requestBody": {
                    "description": "업데이트할 영업시간 및 아이디",
                    "required": true,
                    "content": {
                        "application/json": {
                            "schema": {
                                "properties": {
                                    "b_hour_id": {
                                        "description": "영업시간 아이디",
                                        "type": "integer",
                                        "example": 1
                                    },
                                    "s_time": {
                                        "description": "영업 시작",
                                        "type": "time",
                                        "example": "08:00:00"
                                    },
                                    "e_time": {
                                        "description": "영업 종료",
                                        "type": "time",
                                        "example": "21:00:00"
                                    }
                                },
                                "type": "object"
                            }
                        }
                    }
                },
                "responses": {
                    "200": {
                        "description": "OK"
                    },
                    "422": {
                        "description": "Validation Exception"
                    },
                    "500": {
                        "description": "Fail"
                    }
                }
            }
        },
        "/api/admin/salon-hour/{id}": {
            "delete": {
                "tags": [
                    "미용실"
                ],
                "summary": "영업시간 삭제",
                "description": "미용실 영업시간 삭제",
                "operationId": "3718f8de345a7d020f0c7c3fcb346f3d",
                "parameters": [
                    {
                        "name": "id",
                        "in": "path",
                        "description": "삭제할 영업시간 값의 아이디",
                        "required": true,
                        "schema": {
                            "type": "integer"
                        }
                    }
                ],
                "responses": {
                    "200": {
                        "description": "Success"
                    },
                    "422": {
                        "description": "Validation Exception"
                    },
                    "500": {
                        "description": "Fail"
                    }
                }
            }
        },
        "/api/admin/salon-category": {
            "get": {
                "tags": [
                    "미용실"
                ],
                "summary": "카테고리 목록",
                "description": "미용실 카테고리 목록",
                "operationId": "99a06e4d5ec40321870dabf03cfaf36d",
                "responses": {
                    "200": {
                        "description": "Success"
                    },
                    "500": {
                        "description": "Fail"
                    }
                }
            },
            "post": {
                "tags": [
                    "미용실"
                ],
                "summary": "카테고리 생성",
                "description": "미용실 카테고리 생성",
                "operationId": "8b173f291381060088f2a1c72fc4c6ae",
                "requestBody": {
                    "description": "카테고리 관련 정보",
                    "required": true,
                    "content": {
                        "application/json": {
                            "schema": {
                                "properties": {
                                    "category_name": {
                                        "description": "카테고리 명",
                                        "type": "string",
                                        "example": "커트"
                                    }
                                },
                                "type": "object"
                            }
                        }
                    }
                },
                "responses": {
                    "201": {
                        "description": "Created"
                    },
                    "422": {
                        "description": "Validation Exception"
                    },
                    "500": {
                        "description": "Fail"
                    }
                }
            },
            "patch": {
                "tags": [
                    "미용실"
                ],
                "summary": "카테고리 수정",
                "description": "카테고리 이름 수정",
                "operationId": "94588bf364a879d920a7a0b38c7d8209",
                "requestBody": {
                    "description": "카테고리 수정을 위한 정보",
                    "required": true,
                    "content": {
                        "application/json": {
                            "schema": {
                                "properties": {
                                    "category_id": {
                                        "description": "카테고리 아이디",
                                        "type": "integer",
                                        "example": 1
                                    },
                                    "category_name": {
                                        "description": "카테고리 명",
                                        "type": "string",
                                        "example": "엄준식"
                                    }
                                },
                                "type": "object"
                            }
                        }
                    }
                },
                "responses": {
                    "200": {
                        "description": "Success"
                    },
                    "422": {
                        "description": "Validation Exception"
                    },
                    "404": {
                        "description": "Model Not Found Exception"
                    },
                    "500": {
                        "description": "Fail"
                    }
                }
            }
        },
        "/api/admin/salon-category/{id}": {
            "delete": {
                "tags": [
                    "미용실"
                ],
                "summary": "카테고리 삭제",
                "description": "미용실 카테고리 삭제",
                "operationId": "54ec001bf01edbcb9f588441c5213f6a",
                "parameters": [
                    {
                        "name": "id",
                        "in": "path",
                        "description": "삭제할 카테고리의 아이디",
                        "required": true,
                        "schema": {
                            "type": "integer"
                        }
                    }
                ],
                "responses": {
                    "200": {
                        "description": "Success"
                    },
                    "500": {
                        "description": "Fail"
                    }
                }
            }
        },
        "/api/admin/salon-service/{id}": {
            "get": {
                "tags": [
                    "미용실"
                ],
                "summary": "카테고리 서비스 목록",
                "description": "미용실 특정 카테고리의 서비스 목록",
                "operationId": "ff42cf6264606d021eddcf79dce9e69e",
                "parameters": [
                    {
                        "name": "id",
                        "in": "path",
                        "description": "찾을 카테고리의 아이디",
                        "required": true,
                        "schema": {
                            "type": "integer"
                        }
                    }
                ],
                "responses": {
                    "200": {
                        "description": "Success"
                    },
                    "500": {
                        "description": "Fail"
                    }
                }
            },
            "delete": {
                "tags": [
                    "미용실"
                ],
                "summary": "서비스 삭제",
                "description": "미용실 서비스 삭제",
                "operationId": "765665a1df52406f7a2430b0b5ddb2ed",
                "parameters": [
                    {
                        "name": "id",
                        "in": "path",
                        "description": "삭제할 서비스의 아이디",
                        "required": true,
                        "schema": {
                            "type": "integer"
                        }
                    }
                ],
                "responses": {
                    "200": {
                        "description": "Success"
                    },
                    "500": {
                        "description": "Fail"
                    }
                }
            }
        },
        "/api/admin/salon-service": {
            "post": {
                "tags": [
                    "미용실"
                ],
                "summary": "서비스 생성",
                "description": "미용실 서비스 생성",
                "operationId": "1edceb78f24fc12d1c7d15c1331e036d",
                "requestBody": {
                    "description": "서비스 관련 정보",
                    "required": true,
                    "content": {
                        "application/json": {
                            "schema": {
                                "properties": {
                                    "category_id": {
                                        "description": "카테고리 아이디",
                                        "type": "integer",
                                        "example": 1
                                    },
                                    "service_name": {
                                        "description": "서비스 명",
                                        "type": "string",
                                        "example": "커트"
                                    },
                                    "price_male": {
                                        "description": "남성 가격",
                                        "type": "string",
                                        "example": "12345"
                                    },
                                    "price_female": {
                                        "description": "여성 가격",
                                        "type": "string",
                                        "example": "54321"
                                    }
                                },
                                "type": "object"
                            }
                        }
                    }
                },
                "responses": {
                    "201": {
                        "description": "Created"
                    },
                    "422": {
                        "description": "Validation Exception"
                    },
                    "500": {
                        "description": "Fail"
                    }
                }
            },
            "patch": {
                "tags": [
                    "미용실"
                ],
                "summary": "서비스 수정",
                "description": "미용실 서비스 수정",
                "operationId": "05437688b4092e9670640a331519a89c",
                "requestBody": {
                    "description": "서비스 수정을 위한 정보",
                    "required": true,
                    "content": {
                        "application/json": {
                            "schema": {
                                "properties": {
                                    "service_id": {
                                        "description": "카테고리 아이디",
                                        "type": "integer",
                                        "example": 1
                                    },
                                    "service_name": {
                                        "description": "카테고리 명",
                                        "type": "string",
                                        "example": "엄준식"
                                    },
                                    "gender": {
                                        "description": "성별",
                                        "type": "string",
                                        "example": "male"
                                    },
                                    "price": {
                                        "description": "가격",
                                        "type": "string",
                                        "example": "20000"
                                    }
                                },
                                "type": "object"
                            }
                        }
                    }
                },
                "responses": {
                    "200": {
                        "description": "Success"
                    },
                    "422": {
                        "description": "Validation Exception"
                    },
                    "404": {
                        "description": "Model Not Found Exception"
                    },
                    "500": {
                        "description": "Fail"
                    }
                }
            }
        },
        "/api/admin/qr": {
            "get": {
                "tags": [
                    "관리자"
                ],
                "summary": "QR코드 생성",
                "description": "QR코드 생성해서 이미지로 반환",
                "operationId": "e226390d94736fbc202f93f996e5de19",
                "responses": {
                    "200": {
                        "description": "Success"
                    },
                    "422": {
                        "description": "Validation Error"
                    }
                }
            }
        },
        "/api/restaurant/semester": {
            "post": {
                "tags": [
                    "학생"
                ],
                "summary": "식수 학기 신청",
                "description": "식수 학기 신청을 처리합니다",
                "operationId": "0f60453fbb985176ae9c93f99e7c5536",
                "requestBody": {
                    "description": "학생 식사 신청 정보",
                    "required": true,
                    "content": {
                        "application/json": {
                            "schema": {
                                "properties": {
                                    "user_id": {
                                        "description": "사용자 ID",
                                        "type": "string",
                                        "example": "1"
                                    },
                                    "menu_type": {
                                        "description": "식사유형",
                                        "type": "string",
                                        "example": "A"
                                    },
                                    "payment": {
                                        "description": "입금여부",
                                        "type": "boolean",
                                        "example": "true"
                                    }
                                },
                                "type": "object"
                            }
                        }
                    }
                },
                "responses": {
                    "200": {
                        "description": "Success"
                    },
                    "500": {
                        "description": "Fail"
                    }
                }
            }
        },
        "/api/restaurant/weekend": {
            "post": {
                "tags": [
                    "학생"
                ],
                "summary": "식수 주말 신청",
                "description": "식수 주말 신청을 처리합니다",
                "operationId": "dbb5c91d3fe0431f6e2f02d5f02413e0",
                "requestBody": {
                    "description": "학생 식사 신청 정보",
                    "required": true,
                    "content": {
                        "application/json": {
                            "schema": {
                                "properties": {
                                    "user_id": {
                                        "description": "사용자 ID",
                                        "type": "string",
                                        "example": "1"
                                    },
                                    "menu_type": {
                                        "description": "식사유형",
                                        "type": "string",
                                        "example": "A"
                                    },
                                    "sat": {
                                        "description": "토요일",
                                        "type": "boolean",
                                        "example": "true"
                                    },
                                    "sun": {
                                        "description": "일요일",
                                        "type": "boolean",
                                        "example": "true"
                                    }
                                },
                                "type": "object"
                            }
                        }
                    }
                },
                "responses": {
                    "200": {
                        "description": "Success"
                    },
                    "500": {
                        "description": "Fail"
                    }
                }
            }
        },
        "/api/user/login": {
            "get": {
                "tags": [
                    "학생"
                ],
                "summary": "로그인",
                "description": "유저 Google 로그인",
                "operationId": "41d97a651bbdd987dda255209cc578cd",
                "responses": {
                    "200": {
                        "description": "Success"
                    },
                    "500": {
                        "description": "Fail"
                    }
                }
            }
        },
        "/api/user/logout": {
            "get": {
                "tags": [
                    "학생"
                ],
                "summary": "로그아웃",
                "description": "유저 Google 로그아웃",
                "operationId": "c9a0f004b340af9bd5848972fba78d08",
                "responses": {
                    "200": {
                        "description": "Success"
                    },
                    "500": {
                        "description": "Fail"
                    }
                }
            }
        },
        "/api/user": {
            "get": {
                "tags": [
                    "학생"
                ],
                "summary": "승인 혹은 미승인 학생 목록",
                "description": "파라미터 값에 맞는 학생을 users 배열에 반환",
                "operationId": "d317735745268edceff53dba390dcceb",
                "requestBody": {
                    "description": "승인 학생 조회의 경우 true, 미승인 학생 조회의 경우 false, 전체 조회 시에는 body 없이 요청만",
                    "required": false,
                    "content": {
                        "application/json": {
                            "schema": {
                                "properties": {
                                    "type": {
                                        "description": "승인 미승인 여부",
                                        "type": "boolean",
                                        "example": true
                                    }
                                },
                                "type": "object"
                            }
                        }
                    }
                },
                "responses": {
                    "200": {
                        "description": "Success"
                    },
                    "500": {
                        "description": "Server Error"
                    }
                }
            },
            "patch": {
                "tags": [
                    "학생"
                ],
                "summary": "개인정보 수정",
                "description": "유저 개인정보 수정",
                "operationId": "bb324e71bdf9f967232c58475ecbe350",
                "requestBody": {
                    "description": "수정할 유저의 정보",
                    "required": true,
                    "content": {
                        "application/json": {
                            "schema": {
                                "properties": {
                                    "user_id": {
                                        "description": "정보를 수정할 유저의 아이디",
                                        "type": "number",
                                        "example": 1
                                    },
                                    "student_id": {
                                        "description": "정보를 수정할 유저의 아이디",
                                        "type": "string",
                                        "example": 1
                                    },
                                    "name": {
                                        "description": "변경할 이름",
                                        "type": "string",
                                        "example": "hyun"
                                    },
                                    "phone_number": {
                                        "description": "변경할 휴대폰 번호",
                                        "type": "string",
                                        "example": "01012345678"
                                    }
                                },
                                "type": "object"
                            }
                        }
                    }
                },
                "responses": {
                    "200": {
                        "description": "Success"
                    },
                    "500": {
                        "description": "Fail"
                    }
                }
            }
        },
        "/api/user/foreigner": {
            "post": {
                "tags": [
                    "학생"
                ],
                "summary": "회원가입",
                "description": "유학생 회원가입",
                "operationId": "cbdb5292e9560ce496c12b8a0cc29f96",
                "requestBody": {
                    "description": "회원가입 정보",
                    "required": true,
                    "content": {
                        "application/json": {
                            "schema": {
                                "properties": {
                                    "name": {
                                        "description": "사용자 이름",
                                        "type": "string",
                                        "example": "관리자"
                                    },
                                    "phone_number": {
                                        "description": "전화번호",
                                        "type": "string",
                                        "example": "01012345678"
                                    },
                                    "email": {
                                        "description": "이메일",
                                        "type": "string",
                                        "example": "admin@gmail.com"
                                    },
                                    "password": {
                                        "description": "비밀번호",
                                        "type": "string",
                                        "example": "admin123"
                                    }
                                },
                                "type": "object"
                            }
                        }
                    }
                },
                "responses": {
                    "200": {
                        "description": "Success"
                    },
                    "500": {
                        "description": "Fail"
                    }
                }
            }
        },
        "/api/user/foreigner/login": {
            "post": {
                "tags": [
                    "학생"
                ],
                "summary": "로그인",
                "description": "유학생 로그인",
                "operationId": "39e923277f2d84a89b3171e6d98227b4",
                "requestBody": {
                    "description": "회원가입 정보",
                    "required": true,
                    "content": {
                        "application/json": {
                            "schema": {
                                "properties": {
                                    "email": {
                                        "description": "이메일",
                                        "type": "string",
                                        "example": "admin@gmail.com"
                                    },
                                    "password": {
                                        "description": "비밀번호",
                                        "type": "string",
                                        "example": "admin123"
                                    }
                                },
                                "type": "object"
                            }
                        }
                    }
                },
                "responses": {
                    "200": {
                        "description": "Success"
                    },
                    "500": {
                        "description": "Fail"
                    }
                }
            }
        },
        "/api/user/approve": {
            "patch": {
                "tags": [
                    "학생"
                ],
                "summary": "회원가입 승인",
                "description": "유학생 회원가입 승인 (거부 시 계정 정보 삭제 됨)",
                "operationId": "104985906292896376471e2145beb3e5",
                "requestBody": {
                    "description": "아이디 및 승인 여부",
                    "required": true,
                    "content": {
                        "application/json": {
                            "schema": {
                                "properties": {
                                    "admin_id": {
                                        "description": "권한을 부여할 유학생의 아이디",
                                        "type": "number",
                                        "example": 1
                                    },
                                    "approve": {
                                        "description": "유학생 회원가입 승인 여부",
                                        "type": "boolean",
                                        "example": false
                                    }
                                },
                                "type": "object"
                            }
                        }
                    }
                },
                "responses": {
                    "200": {
                        "description": "Success"
                    },
                    "500": {
                        "description": "Fail"
                    }
                }
            }
        },
        "/api/user/{id}": {
            "delete": {
                "tags": [
                    "학생"
                ],
                "summary": "탈퇴",
                "description": "일반 학생 및 유학생 탈퇴",
                "operationId": "30e379b8383ecf7961ec3abd88fe2c70",
                "parameters": [
                    {
                        "name": "id",
                        "in": "path",
                        "description": "탈퇴할 학생, 유학생의 아이디",
                        "required": true,
                        "schema": {
                            "type": "integer"
                        }
                    }
                ],
                "responses": {
                    "200": {
                        "description": "Success"
                    },
                    "500": {
                        "description": "Fail"
                    }
                }
            }
        },
        "/api/user/verify-email/{id}": {
            "get": {
                "tags": [
                    "학생"
                ],
                "summary": "이메일 중복 확인",
                "description": "학생 이메일 중복 확인",
                "operationId": "969d4ec34856375027650a1d786876ec",
                "parameters": [
                    {
                        "name": "id",
                        "in": "path",
                        "description": "중복을 확인할 학생의 이메일",
                        "required": true,
                        "schema": {
                            "type": "string"
                        }
                    }
                ],
                "responses": {
                    "200": {
                        "description": "Success"
                    },
                    "422": {
                        "description": "Validation Error"
                    }
                }
            }
        },
        "/api/user/salon-reservation": {
            "get": {
                "tags": [
                    "학생"
                ],
                "summary": "예약 정보 가져오기",
                "description": "현재 로그인한 유저의 예약 정보를 불러옴",
                "operationId": "55d9748d14e02505a759ddd22951e498",
                "responses": {
                    "200": {
                        "description": "Success"
                    },
                    "500": {
                        "description": "Fail"
                    }
                }
            },
            "post": {
                "tags": [
                    "미용실"
                ],
                "summary": "예약",
                "description": "학생 미용실 예약",
                "operationId": "c2d8397953aa3c0e3b8c890e2ad26b2c",
                "requestBody": {
                    "description": "예약 관련 정보",
                    "required": true,
                    "content": {
                        "application/json": {
                            "schema": {
                                "properties": {
                                    "salon_service_id": {
                                        "description": "미용실 서비스 아이디",
                                        "type": "integer",
                                        "example": 1
                                    },
                                    "user_id": {
                                        "description": "유저 아이디",
                                        "type": "integer",
                                        "example": 1
                                    },
                                    "r_date": {
                                        "description": "예약 날짜",
                                        "type": "string",
                                        "format": "date",
                                        "example": "2024-01-01"
                                    },
                                    "r_time": {
                                        "description": "예약 시간",
                                        "type": "time",
                                        "example": "12:12:12"
                                    }
                                },
                                "type": "object"
                            }
                        }
                    }
                },
                "responses": {
                    "201": {
                        "description": "Success"
                    },
                    "422": {
                        "description": "Validation Exception"
                    },
                    "500": {
                        "description": "Failed to save"
                    }
                }
            }
        },
        "/api/admin/salon-reservation/{id}": {
            "delete": {
                "tags": [
                    "미용실"
                ],
                "summary": "예약 취소",
                "description": "미용실 예약 취소",
                "operationId": "23e2c8be7b062c0ab82206bdf2d1cc5c",
                "parameters": [
                    {
                        "name": "id",
                        "in": "path",
                        "description": "취소할 예약의 아이디",
                        "required": true,
                        "schema": {
                            "type": "integer"
                        }
                    }
                ],
                "responses": {
                    "200": {
                        "description": "Success"
                    },
                    "422": {
                        "description": "Validation Exception"
                    },
                    "500": {
                        "description": "Fail"
                    }
                }
            }
        }
    }
}